nuts/__init__.py
nuts/cron.py
nuts/job.py
nuts/queue.py
nuts/worker.py
nuts/workflow.py
nuts_scheduler-0.4.0.dist-info/licenses/LICENSE
nuts_scheduler-0.4.0.dist-info/METADATA
nuts_scheduler-0.4.0.dist-info/WHEEL
nuts_scheduler-0.4.0.dist-info/top_level.txt
nuts_scheduler-0.4.0.dist-info/RECORD
