Metadata-Version: 2.4
Name: nuts-scheduler
Version: 0.4.0
Summary: A Redis backed job runner
Author-email: Sam Huffman <huffmsa@gmail.com>
License: MIT
Project-URL: Homepage, https://github.com/huffmsa/nuts
Project-URL: Issues, https://github.com/huffmsa/nuts/issues
Classifier: Programming Language :: Python :: 3
Classifier: Operating System :: OS Independent
Classifier: License :: OSI Approved :: MIT License
Requires-Python: >=3.8
License-File: LICENSE
Requires-Dist: python-dateutil==2.9.0.post0
Requires-Dist: redis==5.2.1
Dynamic: license-file
